{
  "ein": "237230232",
  "irs_name": "TUALATIN UNITED METHODIST CHURCH",
  "irs_city": "TUALATIN",
  "irs_state": "OR",
  "irs_zip": "97062-9369",
  "latitude": 45.374598474393,
  "longitude": -122.760529162524,
  "geocode_source": "address",
  "google_result_title": "Tualatin United Methodist Church",
  "website": "https://tualatinumc.org/",
  "website_hostname": "tualatinumc.org",
  "match_reason": "The name matches exactly, the location is the same city, and the website appears to be owned by the specific church.",
  "match_type": "website"
}
