{
  "ein": "261790098",
  "irs_name": "EKKLESIA EUGENE",
  "irs_city": "EUGENE",
  "irs_state": "OR",
  "irs_zip": "97408-7335",
  "latitude": 44.089655298124,
  "longitude": -123.061150710493,
  "geocode_source": "address",
  "google_result_title": "Ekklesia Eugene",
  "website": "https://www.ekklesiaeugene.org/",
  "website_hostname": "ekklesiaeugene.org",
  "match_reason": "The church name matches exactly, the location is Eugene which matches the IRS city, and the content includes specific address and service times.",
  "match_type": "website"
}
