{
  "ein": "436043847",
  "irs_name": "VILLAGE MISSIONS",
  "irs_city": "DALLAS",
  "irs_state": "OR",
  "irs_zip": "97338-0197",
  "google_result_title": "Missionary Summary - Donate - Village Missions",
  "website": "https://give.villagemissions.org/donate/missionaries/missionary-summary",
  "website_hostname": "give.villagemissions.org",
  "match_reason": "The website matches the church name exactly, includes the same PO Box address in Dallas, OR, and appears to be the primary site for Village Missions.",
  "match_type": "website"
}
