{
  "ein": "462888792",
  "irs_name": "PACIFIC RIM MISSIONS INTERNATIONAL",
  "irs_city": "FAIRVIEW",
  "irs_state": "OR",
  "irs_zip": "97024-6746",
  "latitude": 45.548708645008,
  "longitude": -122.450694077915,
  "geocode_source": "address",
  "google_result_title": "Contact | prmi - Pacific Rim Missions",
  "website": "https://www.pacificrimmissions.org/contact",
  "website_hostname": "pacificrimmissions.org",
  "match_reason": "The website name and content exactly match the church's official name and location.",
  "match_type": "website"
}
