{
  "ein": "205415960",
  "irs_name": "IGLESIA DE JESUCRISTO CASA DEL ALFARERO",
  "irs_city": "NORTHRIDGE",
  "irs_state": "CA",
  "irs_zip": "91324-4546",
  "google_result_title": "Iglesia de Jesucristo “Casa del Alfarero” | Los Angeles CA",
  "website": "https://www.facebook.com/p/Iglesia-de-Jesucristo-Casa-del-Alfarero-100067813626324/",
  "website_hostname": "facebook.com",
  "match_reason": "The name in the title matches exactly, and Northridge is a neighborhood of Los Angeles.",
  "match_type": "social_media",
  "last_updated": "2026-03-20"
}
