{
  "ein": "237112024",
  "irs_name": "CALVARY CHAPEL OF BIG BEAR",
  "irs_city": "BIG BEAR CITY",
  "irs_state": "CA",
  "irs_zip": "92314-9615",
  "latitude": 34.266707165269,
  "longitude": -116.853431854097,
  "geocode_source": "address",
  "google_result_title": "Calvary Chapel of Big Bear - Home",
  "website": "https://www.ccbigbear.com/",
  "website_hostname": "ccbigbear.com",
  "match_reason": "The website name, address, and contact information match the IRS record exactly.",
  "match_type": "website"
}
