{
  "ein": "237375989",
  "irs_name": "CHURCH OF CHRIST IN ALAMEDA",
  "irs_city": "ALAMEDA",
  "irs_state": "CA",
  "irs_zip": "94501-2832",
  "latitude": 37.767685988998,
  "longitude": -122.247115458798,
  "geocode_source": "address",
  "google_result_title": "Church of Christ Alameda CA",
  "website": "https://www.churchofchristalamedaca.com/",
  "website_hostname": "churchofchristalamedaca.com",
  "match_reason": "The name matches exactly and the location details are correct for Alameda, CA.",
  "match_type": "website"
}
