{
  "ein": "237448575",
  "irs_name": "WESTSIDE CHURCH OF CHRIST OF LOS ANGELES",
  "irs_city": "LOS ANGELES",
  "irs_state": "CA",
  "irs_zip": "90018-3704",
  "latitude": 34.025644402886,
  "longitude": -118.322783648434,
  "geocode_source": "address",
  "google_result_title": "The Westside Church - Los Angeles, CA",
  "website": "https://thewestsidechurch.com/",
  "website_hostname": "thewestsidechurch.com",
  "match_reason": "The name and location match, and the content is from the church's official site.",
  "match_type": "website"
}
