{
  "ein": "272409190",
  "irs_name": "IGLESIA DE CRISTO MINISTERIOS CASA DE GRACIA",
  "irs_city": "LA PUENTE",
  "irs_state": "CA",
  "irs_zip": "91746-2910",
  "latitude": 34.035719547783,
  "longitude": -117.982954180533,
  "geocode_source": "address",
  "google_result_title": "Ministerios Casa De Gracia | La Puente CA",
  "website": "https://www.facebook.com/casadegraciausa/?locale=es_LA",
  "website_hostname": "facebook.com",
  "match_reason": "The title and snippet match the church name exactly, include the correct location, and appear to be the official page.",
  "match_type": "social_media",
  "last_updated": "2026-03-20"
}
