{
  "ein": "273979048",
  "irs_name": "PASTOR OF SAINT JUDE SHRINE OF THE WEST CATHOLIC PARISH IN SAN DIEGO",
  "irs_city": "SAN DIEGO",
  "irs_state": "CA",
  "irs_zip": "92186-5728",
  "google_result_title": "Saint Jude Shrine of the West | San Diego CA",
  "website": "https://www.facebook.com/SaintJudeSD/",
  "website_hostname": "facebook.com",
  "match_reason": "The title and snippet match the church name exactly, include the correct city and state, and appear to be the official page.",
  "match_type": "social_media",
  "last_updated": "2026-03-20"
}
