{
  "ein": "300345868",
  "irs_name": "MISION CRISTIANA RESTAURACION",
  "irs_city": "HAYWARD",
  "irs_state": "CA",
  "irs_zip": "94544-2869",
  "latitude": 37.64786453211,
  "longitude": -122.086918350169,
  "geocode_source": "address",
  "google_result_title": "Contacto - MCR",
  "website": "https://www.mcrestauracion.org/contacto",
  "website_hostname": "mcrestauracion.org",
  "match_reason": "The name matches exactly and the location in Hayward, CA is correct.",
  "match_type": "website"
}
