{
  "ein": "330021741",
  "irs_name": "THE VIETNAMESE DISTRICT OF THE CHRISTIAN AND MISSIONARY ALLIANCE",
  "irs_city": "FULLERTON",
  "irs_state": "CA",
  "irs_zip": "92837-0468",
  "google_result_title": "Giao Hat Viet Nam Hoa Ky | Anaheim CA - Facebook",
  "website": "https://www.facebook.com/VietnameseDistrict/",
  "website_hostname": "facebook.com",
  "match_reason": "Title matches church name in Vietnamese and location Anaheim CA is near Fullerton.",
  "match_type": "social_media",
  "last_updated": "2026-03-20"
}
