{
  "ein": "330024164",
  "irs_name": "KOREAN CHURCH OF ORANGE COUNTY",
  "irs_city": "WESTMINSTER",
  "irs_state": "CA",
  "irs_zip": "92683-5149",
  "latitude": 33.754301688038,
  "longitude": -117.972437847932,
  "geocode_source": "address",
  "google_result_title": "오렌지카운티 한인교회 (Korean Church of Orange County)",
  "website": "https://www.crcna.org/churches/1551",
  "website_hostname": "crcna.org",
  "match_reason": "The website matches the church name exactly, includes the correct address and service times, and appears to be owned by the specific local congregation.",
  "match_type": "website",
  "last_updated": "2026-03-21"
}
