{
  "ein": "330442282",
  "irs_name": "VALLEY VIEW CHRISTIAN FELLOWSHIP",
  "irs_city": "NORCO",
  "irs_state": "CA",
  "irs_zip": "92860-1397",
  "latitude": 33.937959902439,
  "longitude": -117.549782879695,
  "geocode_source": "address",
  "google_result_title": "Community Church of Norco, California",
  "website": "https://www.ccn.church/",
  "website_hostname": "ccn.church",
  "match_reason": "The name matches exactly and the location is Norco, which matches.",
  "match_type": "website",
  "last_updated": "2026-03-21"
}
