{
  "ein": "330487225",
  "irs_name": "JESS RANCH COMMUNITY CHURCH",
  "irs_city": "APPLE VALLEY",
  "irs_state": "CA",
  "irs_zip": "92308-7583",
  "latitude": 34.461799975003,
  "longitude": -117.242268653902,
  "geocode_source": "address",
  "google_result_title": "The Community Church at Jess Ranch",
  "website": "https://www.jessranchchurch.org/",
  "website_hostname": "jessranchchurch.org",
  "match_reason": "The name 'JESS RANCH COMMUNITY CHURCH' matches the URL and content, and the address (11537 Apple Valley Rd, Apple Valley, CA 92308) is correct.",
  "match_type": "website"
}
