{
  "ein": "330514614",
  "irs_name": "THE CHURCH IN MORENO VALLEY",
  "irs_city": "MORENO VALLEY",
  "irs_state": "CA",
  "irs_zip": "92555-2250",
  "latitude": 33.936521832876,
  "longitude": -117.204666282637,
  "geocode_source": "address",
  "google_result_title": "MCA the Church Moreno Valley",
  "website": "https://mcathechurch.com/",
  "website_hostname": "mcathechurch.com",
  "match_reason": "The name 'MCA the Church Moreno Valley' matches 'THE CHURCH IN MORENO VALLEY', and the location is identical.",
  "match_type": "website",
  "last_updated": "2026-03-21"
}
