{
  "ein": "330623280",
  "irs_name": "CHRIST GOSPEL CHURCH OF LONG BEACH",
  "irs_city": "BELLFLOWER",
  "irs_state": "CA",
  "irs_zip": "90706-5750",
  "latitude": 33.882010831897,
  "longitude": -118.133389581042,
  "geocode_source": "address",
  "google_result_title": "Christ Gospel Church of Long Beach | Bellflower CA - Facebook",
  "website": "https://www.facebook.com/christgospelchurchlb/",
  "website_hostname": "facebook.com",
  "match_reason": "The name matches exactly and the location (Bellflower) is in the same city as the IRS record.",
  "match_type": "social_media"
}
