{
  "ein": "330624885",
  "irs_name": "HOLY FAITH TEMPLE MINISTRY",
  "irs_city": "RIVERSIDE",
  "irs_state": "CA",
  "irs_zip": "92505-3026",
  "latitude": 33.906981057776,
  "longitude": -117.472782982606,
  "geocode_source": "address",
  "google_result_title": "Statement of Faith - Riverside Faith Temple",
  "website": "https://riversidefaithtemple.org/statement-faith/",
  "website_hostname": "riversidefaithtemple.org",
  "match_reason": "The church name 'Riverside Faith Temple Ministries' is a plausible variation of the IRS name 'HOLY FAITH TEMPLE MINISTRY', and the city matches (Riverside, CA).",
  "match_type": "website",
  "last_updated": "2026-03-20"
}
