{
  "ein": "330792628",
  "irs_name": "LIGHTHOUSE MINISTRIES USA",
  "irs_city": "APPLE VALLEY",
  "irs_state": "CA",
  "irs_zip": "92308-5113",
  "google_result_title": "Apple Valley Campus - lighthouse hesperia",
  "website": "https://www.lighthousehesperia.com/apple-valley-ca.html",
  "website_hostname": "lighthousehesperia.com",
  "match_reason": "The website provides the exact church name and matches the location in Apple Valley, CA.",
  "match_type": "website",
  "last_updated": "2026-03-20"
}
