{
  "ein": "330951839",
  "irs_name": "CENTRO EVANGELISTICO RIOS DE AQUA VIVA",
  "irs_city": "STANTON",
  "irs_state": "CA",
  "irs_zip": "90680-3005",
  "latitude": 33.803854453325,
  "longitude": -117.993328327217,
  "geocode_source": "address",
  "google_result_title": "Centro Evangelistico \"Rios de Agua Viva\", Stanton - Facebook",
  "website": "https://www.facebook.com/p/Centro-Evangelistico-Rios-de-Agua-Viva-Stanton-100071252522068/",
  "website_hostname": "facebook.com",
  "match_reason": "The name matches exactly, and the address is in Stanton, CA.",
  "match_type": "social_media",
  "last_updated": "2026-03-20"
}
