{
  "ein": "334605673",
  "irs_name": "SPOROS MISSION CHURCH",
  "irs_city": "LA JOLLA",
  "irs_state": "CA",
  "irs_zip": "92037-1140",
  "latitude": 32.874803102489,
  "longitude": -117.244443106212,
  "geocode_source": "address",
  "google_result_title": "施普絡世宣教中心",
  "website": "https://sporosmission.org/",
  "website_hostname": "sporosmission.org",
  "match_reason": "The name matches exactly and the location is in La Jolla, CA as stated by both the IRS record and the website.",
  "match_type": "website"
}
