{
  "ein": "421560176",
  "irs_name": "PRAISE COVENANT CHURCH INTERNATIONAL",
  "irs_city": "FAIRFIELD",
  "irs_state": "CA",
  "irs_zip": "94533-3106",
  "latitude": 38.268276758113,
  "longitude": -122.049862641967,
  "geocode_source": "address",
  "google_result_title": "Praise Covenant Church (@praisecovenantchurch) - Instagram",
  "website": "https://www.instagram.com/praisecovenantchurch/",
  "website_hostname": "instagram.com",
  "match_reason": "The name matches exactly and the location is in the same city.",
  "match_type": "social_media"
}
