{
  "ein": "452654513",
  "irs_name": "BAHAIS OF MALIBU",
  "irs_city": "MALIBU",
  "irs_state": "CA",
  "irs_zip": "90265-2858",
  "latitude": 34.040770885439,
  "longitude": -118.771799354927,
  "geocode_source": "address",
  "google_result_title": "Malibu Bahá'í",
  "website": "https://www.malibubahai.org/",
  "website_hostname": "malibubahai.org",
  "match_reason": "The name matches exactly, and Malibu in the URL is the same city as listed in the IRS record.",
  "match_type": "website",
  "last_updated": "2026-03-20"
}
