{
  "ein": "453652944",
  "irs_name": "LOVE FOCUS INTERNATIONAL ASSOCIATION",
  "irs_city": "MERCED",
  "irs_state": "CA",
  "irs_zip": "95348-3410",
  "latitude": 37.31494405259,
  "longitude": -120.471299574721,
  "geocode_source": "address",
  "google_result_title": "Love Focus International Association",
  "website": "https://www.lovefocusis.com/",
  "website_hostname": "lovefocusis.com",
  "match_reason": "The name matches exactly, the location is in the same city (Merced), and it appears to be the official website with mailing address information.",
  "match_type": "website"
}
