{
  "ein": "453674111",
  "irs_name": "NEW LIFE GOSPEL CHINESE CHRISTIAN CHURCH",
  "irs_city": "FREMONT",
  "irs_state": "CA",
  "irs_zip": "94538-3170",
  "latitude": 37.506295223358,
  "longitude": -121.972510536994,
  "geocode_source": "address",
  "google_result_title": "New Life Fremont",
  "website": "https://www.newlifefremont.org/",
  "website_hostname": "newlifefremont.org",
  "match_reason": "The name is an exact match and the location is in the same city as stated by IRS.",
  "match_type": "website"
}
