{
  "ein": "461338203",
  "irs_name": "THE JOURNEY CHURCH CA",
  "irs_city": "MENIFEE",
  "irs_state": "CA",
  "irs_zip": "92586-2509",
  "latitude": 33.710819606066,
  "longitude": -117.193260545441,
  "geocode_source": "address",
  "google_result_title": "Locations - Sandals Church",
  "website": "https://sandalschurch.com/locations/",
  "website_hostname": "sandalschurch.com",
  "match_reason": "The church name matches as a specific location of Sandals Church, and the address in Menifee is correct.",
  "match_type": "website"
}
