{
  "ein": "461743209",
  "irs_name": "GURDUWARA SINGH SABHA OF TULARE COUNTY",
  "irs_city": "VISALIA",
  "irs_state": "CA",
  "irs_zip": "93277-9473",
  "latitude": 36.326116940984,
  "longitude": -119.346893479474,
  "geocode_source": "address",
  "google_result_title": "Sikh Temple Visalia - Facebook",
  "website": "https://www.facebook.com/Worship559/",
  "website_hostname": "facebook.com",
  "match_reason": "The title and snippet match the church name, and the location is in the same city.",
  "match_type": "social_media",
  "last_updated": "2026-03-21"
}
