{
  "ein": "462737668",
  "irs_name": "SHIRDI SAI TEMPLE",
  "irs_city": "TARZANA",
  "irs_state": "CA",
  "irs_zip": "91356-1024",
  "google_result_title": "Shirdi Sai Temple Los Angeles | Shirdi Sai Temple – Tarzana, CA",
  "website": "https://www.shirdisaitempleusa.org/",
  "website_hostname": "shirdisaitempleusa.org",
  "match_reason": "The website name and content match the church's exact name, and the location is identical (6020 Melvin Ave, Tarzana).",
  "match_type": "website",
  "last_updated": "2026-03-20"
}
