{
  "ein": "510203047",
  "irs_name": "AGLOW INTERNATIONAL",
  "irs_city": "MISSION VIEJO",
  "irs_state": "CA",
  "irs_zip": "92692-5035",
  "latitude": 33.58852062656,
  "longitude": -117.655890921347,
  "geocode_source": "address",
  "google_result_title": "Aglow International: Home",
  "website": "https://aglow.org/",
  "website_hostname": "aglow.org",
  "match_reason": "The website name and content clearly match Aglow International, though the physical address is not provided on the homepage.",
  "match_type": "website"
}
