{
  "ein": "770324076",
  "irs_name": "SIERRA VIEW JUNIOR ACADEMY",
  "irs_city": "EXETER",
  "irs_state": "CA",
  "irs_zip": "93221-0000",
  "google_result_title": "Sierra View Junior Academy – Planet Earth Generic Website Template",
  "website": "https://www.sierraviewjunioracademy.org/",
  "website_hostname": "sierraviewjunioracademy.org",
  "match_reason": "The website name matches exactly with the church's name, and Exeter is listed as the city in both records.",
  "match_type": "website"
}
