{
  "ein": "811868939",
  "irs_name": "CHURCH AT THE RED DOOR",
  "irs_city": "LA QUINTA",
  "irs_state": "CA",
  "irs_zip": "92253-2071",
  "latitude": 33.715796055516,
  "longitude": -116.297190119235,
  "geocode_source": "address",
  "google_result_title": "Leadership Team | Church at the Red Door",
  "website": "https://crd.church/leadership-team",
  "website_hostname": "crd.church",
  "match_reason": "The name 'Church at the Red Door' matches exactly, and the location in La Quinta, CA is correct.",
  "match_type": "website",
  "last_updated": "2026-03-20"
}
