{
  "ein": "813256609",
  "irs_name": "IGLESIA BAUTISTA FUNDAMENTAL LA ROCA",
  "irs_city": "ANAHEIM",
  "irs_state": "CA",
  "irs_zip": "92805-6423",
  "latitude": 33.810127431815,
  "longitude": -117.897858275618,
  "geocode_source": "address",
  "google_result_title": "Iglesia Bautista Fundamental La Roca | Anaheim CA - Facebook",
  "website": "https://www.facebook.com/ibflaroca/",
  "website_hostname": "facebook.com",
  "match_reason": "The name matches exactly, and the location Anaheim is correct.",
  "match_type": "social_media",
  "last_updated": "2026-03-21"
}
