{
  "ein": "820661891",
  "irs_name": "NEW CREATION MINISTRIES CHURCH",
  "irs_city": "RIVERSIDE",
  "irs_state": "CA",
  "irs_zip": "92503-7723",
  "google_result_title": "About | newcreationmin - New Creation Ministries Church",
  "website": "https://www.anewcreationministrieschurch.com/about",
  "website_hostname": "anewcreationministrieschurch.com",
  "match_reason": "The name matches exactly ('NEW CREATION MINISTRIES CHURCH'), the location is Riverside, CA, which matches the IRS record, and it contains content specific to the church.",
  "match_type": "website",
  "last_updated": "2026-03-20"
}
