{
  "ein": "820845141",
  "irs_name": "IGLESIA DEL NAZARENO DE ESCONDIDO",
  "irs_city": "ESCONDIDO",
  "irs_state": "CA",
  "irs_zip": "92025-5642",
  "latitude": 33.104082352254,
  "longitude": -117.080288645606,
  "geocode_source": "address",
  "google_result_title": "Escondido First Church of the Nazarene - Facebook",
  "website": "https://www.facebook.com/EFCN.Naz/",
  "website_hostname": "facebook.com",
  "match_reason": "The name and address match exactly.",
  "match_type": "social_media"
}
