{
  "ein": "842650220",
  "irs_name": "CHRUCH WITHOUT BORDERS-IGLESIA SIN FRONTERAS",
  "irs_city": "LOS ANGELES",
  "irs_state": "CA",
  "irs_zip": "90001-3955",
  "latitude": 33.963723858114,
  "longitude": -118.244084292712,
  "geocode_source": "address",
  "google_result_title": "CWOB/Iglesia Sin Fronteras",
  "website": "https://www.cwobchurchiglesia.com/",
  "website_hostname": "cwobchurchiglesia.com",
  "match_reason": "The name matches exactly and the location is in Los Angeles, which matches the IRS record.",
  "match_type": "website"
}
