{
  "ein": "883209840",
  "irs_name": "VIRGIN MARY MOTHER OF THE LIGHT SYRIAC ORTHODOX CHURCH",
  "irs_city": "PORTERVILLE",
  "irs_state": "CA",
  "irs_zip": "93257-6929",
  "latitude": 36.078361737849,
  "longitude": -119.073932063878,
  "geocode_source": "address",
  "google_result_title": "Archdiocese of the Western United States - Syriac Orthodox Church",
  "website": "https://www.soc-wus.org/churches/virginmarymotherodlight.htm",
  "website_hostname": "soc-wus.org",
  "match_reason": "The website content includes an exact match for the church name and provides the correct location in Porterville, CA.",
  "match_type": "website"
}
