{
  "ein": "912171958",
  "irs_name": "HOPE CHRISTIAN FELLOWSHIP",
  "irs_city": "SAN GABRIEL",
  "irs_state": "CA",
  "irs_zip": "91775-2455",
  "latitude": 34.110612128523,
  "longitude": -118.091035882944,
  "geocode_source": "address",
  "google_result_title": "Hope Christian Fellowship – Hope Christian Fellowship San Gabriel",
  "website": "https://hopesg.org/",
  "website_hostname": "hopesg.org",
  "match_reason": "The name matches exactly, the location is identical, and the website provides specific details about the church's address and services.",
  "match_type": "website",
  "last_updated": "2026-03-20"
}
