{
  "ein": "931220294",
  "irs_name": "NEW LIFE CHRISTIAN CHURCH",
  "irs_city": "SN BERNRDNO",
  "irs_state": "CA",
  "irs_zip": "92411-1504",
  "latitude": 34.127509266382,
  "longitude": -117.330560757394,
  "geocode_source": "address",
  "google_result_title": "New Life Christian Church",
  "website": "https://www.new-lifecc.org/",
  "website_hostname": "new-lifecc.org",
  "match_reason": "The name matches exactly, the location in San Bernardino is plausible, and the content includes the church's address and service times.",
  "match_type": "website",
  "last_updated": "2026-03-21"
}
