{
  "ein": "934001301",
  "irs_name": "SAN GABRIEL VALLEY CHINESE SDA CHURCH",
  "irs_city": "ARCADIA",
  "irs_state": "CA",
  "irs_zip": "91006-5067",
  "google_result_title": "聖谷華人教會San Gabriel Valley Chinese Church",
  "website": "https://sangabrielvalleychineseca.adventistchurch.org/",
  "website_hostname": "sangabrielvalleychineseca.adventistchurch.org",
  "match_reason": "Exact name match and location in Arcadia, CA matches IRS record.",
  "match_type": "website",
  "last_updated": "2026-03-20"
}
