{
  "ein": "934696131",
  "irs_name": "SOJOURNERS COMMUNITY FELLOWSHIP INC",
  "irs_city": "NORTHRIDGE",
  "irs_state": "CA",
  "irs_zip": "91324-2053",
  "latitude": 34.249504437285,
  "longitude": -118.536024932511,
  "geocode_source": "address",
  "google_result_title": "Sojourners Community Fellowship",
  "website": "https://www.sojournerscf.com/",
  "website_hostname": "sojournerscf.com",
  "match_reason": "The name matches exactly, the location is Northridge which is a neighborhood of Los Angeles and falls under plausible matching rules.",
  "match_type": "website"
}
