{
  "ein": "941605666",
  "irs_name": "SISTERS OF SAINT JOSEPH OF CARONDELET",
  "irs_city": "SAN LUIS OBISPO",
  "irs_state": "CA",
  "irs_zip": "93405-1615",
  "latitude": 35.294040863958,
  "longitude": -120.671450461407,
  "geocode_source": "address",
  "google_result_title": "Sponsored Ministries - Sisters of St. Joseph of Carondelet",
  "website": "https://csjcarondelet.org/about/ministries/sponsored-ministries/",
  "website_hostname": "csjcarondelet.org",
  "match_reason": "The website belongs to the Sisters of Saint Joseph of Carondelet and lists ministries including one in San Luis Obispo.",
  "match_type": "website",
  "last_updated": "2026-03-21"
}
