{
  "ein": "951924718",
  "irs_name": "SACRED HEART CHURCH",
  "irs_city": "LANCASTER",
  "irs_state": "CA",
  "irs_zip": "93534-2412",
  "latitude": 34.699990165102,
  "longitude": -118.139569514928,
  "geocode_source": "address",
  "google_result_title": "Sacred Heart Church - Lancaster, CA",
  "website": "https://sacredheartlancaster.org/",
  "website_hostname": "sacredheartlancaster.org",
  "match_reason": "The name matches exactly, and the city is the same.",
  "match_type": "website",
  "last_updated": "2026-03-21"
}
