{
  "ein": "952162546",
  "irs_name": "FAITH LUTHERAN CHURCH",
  "irs_city": "YUCAIPA",
  "irs_state": "CA",
  "irs_zip": "92399-4405",
  "latitude": 34.027876932942,
  "longitude": -117.038755423684,
  "geocode_source": "address",
  "google_result_title": "Faith Lutheran Church - Yucaipa",
  "website": "https://faithlutheranyucaipa.org/",
  "website_hostname": "faithlutheranyucaipa.org",
  "match_reason": "The church name and location match exactly.",
  "match_type": "website",
  "last_updated": "2026-03-21"
}
