{
  "ein": "952126162",
  "irs_name": "ST DOROTHYS CHURCH",
  "irs_city": "GLENDORA",
  "irs_state": "CA",
  "irs_zip": "91741-3854",
  "latitude": 34.13317944417,
  "longitude": -117.837774687633,
  "geocode_source": "address",
  "google_result_title": "Mass Times and Confessions - St. Dorothy Catholic Church",
  "website": "https://www.stdorothy.org/apps/pages/index.jsp?uREC_ID=1885893&type=d&pREC_ID=2034381",
  "website_hostname": "stdorothy.org",
  "match_reason": "The church name matches exactly, the location is the same city as listed in IRS records.",
  "match_type": "website"
}
