{
  "ein": "952281403",
  "irs_name": "SAN DIEGO PATHWAY CHRISTIAN FELLOWSHIP",
  "irs_city": "SAN DIEGO",
  "irs_state": "CA",
  "irs_zip": "92111-2612",
  "latitude": 32.810702584021,
  "longitude": -117.181107917416,
  "geocode_source": "address",
  "google_result_title": "Pathway Church San Diego",
  "website": "https://www.pathwaychurchsandiego.org/",
  "website_hostname": "pathwaychurchsandiego.org",
  "match_reason": "The name matches exactly (SAN DIEGO PATHWAY CHRISTIAN FELLOWSHIP) and the location is the same city of San Diego.",
  "match_type": "website",
  "last_updated": "2026-03-20"
}
