{
  "ein": "952428846",
  "irs_name": "UPLAND CHRISTIAN CHURCH",
  "irs_city": "UPLAND",
  "irs_state": "CA",
  "irs_zip": "91786-2272",
  "google_result_title": "Services/Location - Upland Christian Church (DOC)",
  "website": "https://www.uplandchristianchurch.org/servicesandlocation",
  "website_hostname": "uplandchristianchurch.org",
  "match_reason": "The website name and content match the church's exact name and location details provided by IRS.",
  "match_type": "website",
  "last_updated": "2026-03-20"
}
