{
  "ein": "952513699",
  "irs_name": "SAN DIEGO CHRISTIAN FELLOWSHIP",
  "irs_city": "CHULA VISTA",
  "irs_state": "CA",
  "irs_zip": "91911-5848",
  "latitude": 32.595856544227,
  "longitude": -117.063883037777,
  "geocode_source": "address",
  "google_result_title": "San Diego Christian Fellowship | Home",
  "website": "https://sdcfchurch.com/",
  "website_hostname": "sdcfchurch.com",
  "match_reason": "The name and location match exactly.",
  "match_type": "website",
  "last_updated": "2026-03-21"
}
