{
  "ein": "952625772",
  "irs_name": "GOOD SHEPHERD MISSIONARY BAPTIST CHURCH OF LOS ANGELES",
  "irs_city": "LOS ANGELES",
  "irs_state": "CA",
  "irs_zip": "90037-0000",
  "google_result_title": "Good Shepherd Missionary Baptist Church of Los Angeles",
  "website": "https://www.goodshepherdmbcla.com/",
  "website_hostname": "goodshepherdmbcla.com",
  "match_reason": "The name matches exactly, the location is Los Angeles, and the website appears to be the official site of the church.",
  "match_type": "website",
  "last_updated": "2026-03-20"
}
