{
  "ein": "952644227",
  "irs_name": "ST LUKE BAPTIST CHURCH",
  "irs_city": "LONG BEACH",
  "irs_state": "CA",
  "irs_zip": "90810-2308",
  "latitude": 33.818965463741,
  "longitude": -118.211159801523,
  "geocode_source": "address",
  "google_result_title": "St. Luke Holy Baptist Church",
  "website": "https://www.stlukelive.org/",
  "website_hostname": "stlukelive.org",
  "match_reason": "The name matches exactly (considering \"St\" for Saint), and the location is in West Long Beach, which is within Long Beach.",
  "match_type": "website",
  "last_updated": "2026-03-20"
}
