{
  "ein": "952873742",
  "irs_name": "SAINT PAUL BAPTIST CHURCH",
  "irs_city": "OXNARD",
  "irs_state": "CA",
  "irs_zip": "93033-3908",
  "latitude": 34.181490134242,
  "longitude": -119.163603361779,
  "geocode_source": "address",
  "google_result_title": "Service Times & Location - Saint Paul Baptist Church of Oxnard",
  "website": "https://www.saintpaulbaptistoxnard.org/location/",
  "website_hostname": "saintpaulbaptistoxnard.org",
  "match_reason": "The name matches exactly, the location (1777 Statham Boulevard, Oxnard, CA 93033) is correct, and it appears to be the church's official website with service times.",
  "match_type": "website"
}
