{
  "ein": "953077861",
  "irs_name": "BRIGHT STAR CHURCH",
  "irs_city": "LOS ANGELES",
  "irs_state": "CA",
  "irs_zip": "90002-2433",
  "latitude": 33.949120639191,
  "longitude": -118.241814253772,
  "geocode_source": "address",
  "google_result_title": "Bright Star Church of God in Christ - Watts | Los Angeles CA",
  "website": "https://www.facebook.com/brightstarcogicwatts/",
  "website_hostname": "facebook.com",
  "match_reason": "The name matches exactly and the location (Watts, Los Angeles) is within the city.",
  "match_type": "social_media",
  "last_updated": "2026-03-20"
}
