{
  "ein": "953004606",
  "irs_name": "ATASCADERO DOVE CREEK",
  "irs_city": "ATASCADERO",
  "irs_state": "CA",
  "irs_zip": "93422-0000",
  "google_result_title": "Dove Creek Church | Welcome",
  "website": "https://dovecreekchurch.org/",
  "website_hostname": "dovecreekchurch.org",
  "match_reason": "The church name matches exactly, the location is Atascadero which matches the IRS record, and the content indicates it is the official website of Dove Creek Church in Atascadero.",
  "match_type": "website",
  "last_updated": "2026-03-21"
}
