{
  "ein": "953193850",
  "irs_name": "MONTEBELLO FOURSQUARE CHURCH",
  "irs_city": "MONTEBELLO",
  "irs_state": "CA",
  "irs_zip": "90640-5212",
  "latitude": 34.007283947615,
  "longitude": -118.106666500927,
  "geocode_source": "address",
  "google_result_title": "Beverly Boulevard Foursquare Church",
  "website": "https://www.bb4square.org/",
  "website_hostname": "bb4square.org",
  "match_reason": "The name 'Montebello Foursquare Church' matches the search result, and the location (1901 W. Beverly Blvd., Montebello, CA) is in the same city as the IRS record.",
  "match_type": "website",
  "last_updated": "2026-03-20"
}
