{
  "ein": "953214476",
  "irs_name": "RESURRECTION LIFE CHURCH",
  "irs_city": "SANTA ANA",
  "irs_state": "CA",
  "irs_zip": "92705-1769",
  "google_result_title": "Resurrection Life Church | Orange CA - Facebook",
  "website": "https://www.facebook.com/reslifechurchoc/",
  "website_hostname": "facebook.com",
  "match_reason": "The name matches exactly and the location mentions both Santa Ana and Orange which are adjacent cities in the same metro area as the IRS address.",
  "match_type": "social_media",
  "last_updated": "2026-03-20"
}
