{
  "ein": "953337750",
  "irs_name": "STS CONSTANTINE & HELEN GREEK ORTHODOX CHURCH",
  "irs_city": "CARDIFF BY THE SEA",
  "irs_state": "CA",
  "irs_zip": "92007-1500",
  "latitude": 33.01828127714,
  "longitude": -117.255738505655,
  "geocode_source": "address",
  "google_result_title": "Sts. Constantine and Helen Greek Orthodox Church",
  "website": "https://www.stsconstantinehelen.com/",
  "website_hostname": "stsconstantinehelen.com",
  "match_reason": "The church name matches exactly, the location is Cardiff by the Sea which matches the IRS record, and the content includes service details specific to this congregation.",
  "match_type": "website"
}
