{
  "ein": "953622045",
  "irs_name": "GRACE ALLIANCE CHURCH OF THE CHRISTIAN AND MISSIONARY ALLIANCE",
  "irs_city": "CHULA VISTA",
  "irs_state": "CA",
  "irs_zip": "91911-2235",
  "latitude": 32.622746387235,
  "longitude": -117.059131626747,
  "geocode_source": "address",
  "google_result_title": "Grace Alliance Fellowship | Chula Vista CA - Facebook",
  "website": "https://www.facebook.com/p/Grace-Alliance-Fellowship-100066624222452/",
  "website_hostname": "facebook.com",
  "match_reason": "The name in the title matches an abbreviation of the church's name, and the location Chula Vista matches exactly.",
  "match_type": "social_media"
}
