{
  "ein": "953642823",
  "irs_name": "SANTA MONICA SYNAGOGUE",
  "irs_city": "SANTA MONICA",
  "irs_state": "CA",
  "irs_zip": "90404-1206",
  "latitude": 34.02899171835,
  "longitude": -118.484133012484,
  "geocode_source": "address",
  "google_result_title": "The Santa Monica Synagogue",
  "website": "https://www.thesantamonicasynagogue.org/",
  "website_hostname": "thesantamonicasynagogue.org",
  "match_reason": "The website name and content match exactly with the church's name and location provided by IRS.",
  "match_type": "website"
}
