{
  "ein": "953742087",
  "irs_name": "FIRST CHURCH OF GOD",
  "irs_city": "LOMPOC",
  "irs_state": "CA",
  "irs_zip": "93436-9736",
  "latitude": 34.628520152361,
  "longitude": -120.500531554513,
  "geocode_source": "address",
  "google_result_title": "Lompoc Foursquare Church",
  "website": "https://www.lompocfoursquare.com/",
  "website_hostname": "lompocfoursquare.com",
  "match_reason": "The name 'First Church of God' is consistent with 'Lompoc Foursquare Church', and the location in Lompoc, CA matches.",
  "match_type": "website",
  "last_updated": "2026-03-20"
}
