{
  "ein": "953966022",
  "irs_name": "HERITAGE INTERNATIONAL FELLOWSHIP",
  "irs_city": "FULLERTON",
  "irs_state": "CA",
  "irs_zip": "92834-6428",
  "google_result_title": "Heritage Christian Fellowship - Orange",
  "website": "https://www.hcf.cc/",
  "website_hostname": "hcf.cc",
  "match_reason": "The name 'Heritage Christian Fellowship' is a clear variation of 'HERITAGE INTERNATIONAL FELLOWSHIP', the location Orange matches with Fullerton as part of the same metro area, and the website appears to be owned by the church itself.",
  "match_type": "website",
  "last_updated": "2026-03-20"
}
