{
  "ein": "953996168",
  "irs_name": "SHEPHARDS COMMUNITY CHURCH",
  "irs_city": "RESEDA",
  "irs_state": "CA",
  "irs_zip": "91335-4138",
  "latitude": 34.200999848856,
  "longitude": -118.539919051263,
  "geocode_source": "address",
  "google_result_title": "Our History - The Bridge Bible Fellowship",
  "website": "https://bridgebible.church/about/our-history/",
  "website_hostname": "bridgebible.church",
  "match_reason": "The page content mentions Shepherd's Community Church and its history in Woodland Hills and Canoga Park.",
  "match_type": "website"
}
