{
  "ein": "954224602",
  "irs_name": "GALILEE MISSION CHURCH",
  "irs_city": "LOS ANGELES",
  "irs_state": "CA",
  "irs_zip": "90065-2426",
  "latitude": 34.089863819974,
  "longitude": -118.211600287487,
  "geocode_source": "address",
  "google_result_title": "갈릴리선교교회 | GALILEE MISSION CHURCH",
  "website": "https://gmcchurch.com/",
  "website_hostname": "gmcchurch.com",
  "match_reason": "The church name matches exactly, the location is the same city and address, and the website appears to be owned by the specific local congregation.",
  "match_type": "website"
}
