{
  "ein": "954335684",
  "irs_name": "ANGEL FIRE FELLOWSHIP",
  "irs_city": "GRANADA HILLS",
  "irs_state": "CA",
  "irs_zip": "91344-5606",
  "latitude": 34.264975834725,
  "longitude": -118.524044360876,
  "geocode_source": "address",
  "google_result_title": "About | Angel Fire Christian Center",
  "website": "https://www.angelfire-christiancenter.org/about_us",
  "website_hostname": "angelfire-christiancenter.org",
  "match_reason": "The name 'Angel Fire Christian Center' is a DBA for 'Angel Fire Fellowship', and the content mentions the church's history and location in Granada Hills, California.",
  "match_type": "website"
}
