{
  "ein": "954565903",
  "irs_name": "VRIM CHURCH",
  "irs_city": "LA CRESCENTA",
  "irs_state": "CA",
  "irs_zip": "91214-1850",
  "latitude": 34.234666235596,
  "longitude": -118.256732979186,
  "geocode_source": "address",
  "google_result_title": "브림장로교회 (윤혁 목사) | Vrim Presbyterian Church",
  "website": "https://glendalekorean.com/blog-post/%EB%B8%8C%EB%A6%BC%EC%9E%A5%EB%A1%9C%EA%B5%90%ED%9A%8C-%EC%9C%A4%ED%98%81-%EB%AA%A9%EC%82%AC-vrim-presbyterian-church/",
  "website_hostname": "glendalekorean.com",
  "match_reason": "The church name and location match exactly.",
  "match_type": "website"
}
