{
  "ein": "260813813",
  "irs_name": "IGLESIA DE JESUCRISTO PALABRA MIEL",
  "irs_city": "RENTON",
  "irs_state": "WA",
  "irs_zip": "98057-3105",
  "latitude": 47.467804669565,
  "longitude": -122.226587050866,
  "geocode_source": "address",
  "google_result_title": "palabramielrenton.com",
  "website": "http://mobile.palabramielrenton.comcastbiz.net/",
  "website_hostname": "mobile.palabramielrenton.comcastbiz.net",
  "match_reason": "The church name matches exactly, and the location in Renton, WA is correct.",
  "match_type": "website"
}
