{
  "ein": "300124702",
  "irs_name": "WORD OF TRUTH INTERNATIONAL MINISTRIES",
  "irs_city": "TUKWILA",
  "irs_state": "WA",
  "irs_zip": "98168-1931",
  "latitude": 47.505623197912,
  "longitude": -122.290399790654,
  "geocode_source": "address",
  "google_result_title": "Word of Truth International Ministries CRC",
  "website": "https://www.crcna.org/churches/217",
  "website_hostname": "crcna.org",
  "match_reason": "The name matches exactly and the location is the same city as listed in IRS records.",
  "match_type": "website"
}
