{
  "ein": "334323896",
  "irs_name": "PUGET SOUND FOURSQUARE CHURCH WA",
  "irs_city": "TACOMA",
  "irs_state": "WA",
  "irs_zip": "98409-2619",
  "latitude": 47.206188126201,
  "longitude": -122.491127013276,
  "geocode_source": "address",
  "google_result_title": "Puget Sound Foursquare | WELCOME",
  "website": "https://www.pugetsoundfoursquare.com/",
  "website_hostname": "pugetsoundfoursquare.com",
  "match_reason": "The website name and address match exactly.",
  "match_type": "website"
}
