{
  "ein": "352532482",
  "irs_name": "THE ROCK FOUNDATION CHRISTIAN CENTER",
  "irs_city": "SEATTLE",
  "irs_state": "WA",
  "irs_zip": "98118-6018",
  "latitude": 47.520252084441,
  "longitude": -122.260799479598,
  "geocode_source": "address",
  "google_result_title": "Rock Foundation Christian Center | Seattle WA - Facebook",
  "website": "https://www.facebook.com/p/Rock-Foundation-Christian-Center-100067988995581/",
  "website_hostname": "facebook.com",
  "match_reason": "The name matches exactly and the location is in the same city as the IRS record.",
  "match_type": "social_media"
}
