{
  "ein": "454046586",
  "irs_name": "SEATTLE BRIDGE CHURCH",
  "irs_city": "LK FOREST PK",
  "irs_state": "WA",
  "irs_zip": "98155-1710",
  "latitude": 47.774843085956,
  "longitude": -122.281273188694,
  "geocode_source": "address",
  "google_result_title": "Give - Seattle Bridge Church",
  "website": "https://seattlebridgechurch.com/give",
  "website_hostname": "seattlebridgechurch.com",
  "match_reason": "The website name and content exactly match the church's name and address.",
  "match_type": "website"
}
