{
  "ein": "462900766",
  "irs_name": "LEAVEN CHURCH",
  "irs_city": "WOODINVILLE",
  "irs_state": "WA",
  "irs_zip": "98072-8711",
  "latitude": 47.773487808079,
  "longitude": -122.158101589177,
  "geocode_source": "address",
  "google_result_title": "레븐교회 Leaven Church | 시애틀 메트로 Seattle Metro | 한인 교회 ...",
  "website": "https://www.leavenchurch.org/",
  "website_hostname": "leavenchurch.org",
  "match_reason": "The website content matches the church name exactly and provides location details in Kirkland, WA, which is within the Seattle metro area.",
  "match_type": "website"
}
